tests/__init__.py
tests/test.py
viewai/__init__.py
viewai/config.py
viewai/explanations.py
viewai/imports.py
viewai/inputs.py
viewai/logger.py
viewai/modules.py
viewai/plots.py
viewai/xai.py
viewai/utils/_SPOTgreedy.py
viewai/utils/__init__.py
viewai/utils/_clean_simple.py
viewai/utils/_clean_x.py
viewai/utils/_compressed_dataset.py
viewai/utils/_explanation.py
viewai/utils/_histogram.py
viewai/utils/_link.py
viewai/utils/_measure_interactions.py
viewai/utils/_misc.py
viewai/utils/_native.py
viewai/utils/_preprocessor.py
viewai/utils/_privacy.py
viewai/utils/_rank_interactions.py
viewai/utils/_seed.py
viewai/utils/_shap_common.py
viewai/utils/_synthetic.py
viewai/utils/_unify_data.py
viewai/utils/_unify_predict.py
viewai-1.0.0.dist-info/LICENCE.md
viewai-1.0.0.dist-info/METADATA
viewai-1.0.0.dist-info/WHEEL
viewai-1.0.0.dist-info/top_level.txt
viewai-1.0.0.dist-info/RECORD
