Metadata-Version: 2.1
Name: viewai
Version: 1.0.0
Summary: xAI is an open-source package to explain blackbox systems.
Home-page: https://github.com/View-AI/xAI
Author: View AI Team
Author-email: arorashivam@viewai.ca
Classifier: Development Status :: 3 - Alpha
Classifier: Intended Audience :: Developers
Classifier: Natural Language :: English
Classifier: Programming Language :: Python :: 3
Classifier: Programming Language :: Python :: 3.8
Classifier: Programming Language :: Python :: 3.9
Classifier: License :: OSI Approved :: MIT License
Classifier: Operating System :: OS Independent
Requires-Python: >=3.9
License-File: LICENCE.md
Requires-Dist: pandas
Requires-Dist: scikit-learn
Requires-Dist: plotly
Requires-Dist: numpy
Requires-Dist: matplotlib
Requires-Dist: fuzzywuzzy
Requires-Dist: textblob
Requires-Dist: missingpy
Requires-Dist: interpret
Requires-Dist: interpret-core
Requires-Dist: tabulate
Requires-Dist: MarkupSafe
Requires-Dist: Jinja2
Requires-Dist: itsdangerous
Requires-Dist: orjson
Requires-Dist: requests
Requires-Dist: imbalanced-learn
Requires-Dist: lime
